[
  {"question":"qu'est-ce qu'une intelligence artificielle","answer":"Une intelligence artificielle est un programme qui apprend a reconnaitre des motifs et a produire des reponses utiles."},
  {"question":"a quoi sert l'intelligence artificielle","answer":"L'IA sert a aider, automatiser, expliquer, chercher, traduire et generer du contenu."},
  {"question":"comment apprendre plus vite","answer":"Apprends par petites etapes, fais des exercices courts et reviens souvent sur les notions importantes."},
  {"question":"qu'est-ce qu'un modele de langage","answer":"C'est un systeme qui comprend et produit du texte a partir de grandes quantites d'exemples."},
  {"question":"qu'est-ce qu'un chatbot","answer":"Un chatbot est un assistant qui discute avec l'utilisateur en texte ou parfois en voix."},
  {"question":"qu'est-ce que python","answer":"Python est un langage de programmation simple a lire et tres utilise pour l'automatisation et l'IA."},
  {"question":"a quoi sert python","answer":"Python sert a ecrire des scripts, faire des applications, analyser des donnees et creer des outils d'IA."},
  {"question":"comment definir une fonction en python","answer":"On utilise le mot-cle def puis le nom de la fonction et ses parametres entre parenthese."},
  {"question":"qu'est-ce qu'une boucle","answer":"Une boucle repete une action plusieurs fois selon une condition ou une liste d'elements."},
  {"question":"qu'est-ce qu'une condition","answer":"Une condition permet de choisir une action selon si une expression est vraie ou fausse."},
  {"question":"qu'est-ce qu'une variable","answer":"Une variable sert a stocker une valeur pour la reutiliser plus tard."},
  {"question":"qu'est-ce qu'un dictionnaire en python","answer":"Un dictionnaire stocke des couples cle valeur."},
  {"question":"qu'est-ce qu'une liste en python","answer":"Une liste est un ensemble ordonne d'elements."},
  {"question":"qu'est-ce qu'un script","answer":"Un script est un petit programme execute pour accomplir une tache precise."},
  {"question":"qu'est-ce que html","answer":"HTML est le langage qui structure les pages web."},
  {"question":"qu'est-ce que css","answer":"CSS sert a decorer et mettre en forme les pages web."},
  {"question":"qu'est-ce que javascript","answer":"JavaScript sert a rendre une page web interactive."},
  {"question":"qu'est-ce qu'une api","answer":"Une API permet a deux logiciels de communiquer."},
  {"question":"qu'est-ce qu'une base de connaissances","answer":"C'est un ensemble de documents que l'IA peut consulter pour repondre."},
  {"question":"qu'est-ce que le web","answer":"Le web est un ensemble de pages et de services accessibles par internet."},
  {"question":"qu'est-ce qu'internet","answer":"Internet est le reseau mondial qui relie les ordinateurs et les appareils."},
  {"question":"qu'est-ce qu'un navigateur","answer":"Un navigateur permet de consulter les pages web."},
  {"question":"qu'est-ce qu'un serveur","answer":"Un serveur est un ordinateur ou un logiciel qui fournit un service a d'autres machines."},
  {"question":"qu'est-ce que le cloud","answer":"Le cloud permet de stocker et d'executer des services sur des serveurs distants."},
  {"question":"qu'est-ce que le json","answer":"JSON est un format de donnees simple pour representer des objets et des listes."},
  {"question":"qu'est-ce qu'un fichier csv","answer":"Un fichier CSV contient des donnees separees par des virgules ou des points-virgules."},
  {"question":"qu'est-ce qu'un collège","answer":"Le college est un etablissement scolaire entre l'ecole primaire et le lycee."},
  {"question":"qu'est-ce que le lycee","answer":"Le lycee est l'etape scolaire apres le college."},
  {"question":"qu'est-ce qu'un ingenieur","answer":"Un ingenieur conçoit, construit et améliore des systemes, des machines ou des logiciels."},
  {"question":"qu'est-ce qu'un professeur","answer":"Un professeur transmet des connaissances et aide les eleves a progresser."},
  {"question":"qu'est-ce qu'un scientifique","answer":"Un scientifique observe, experiment et cherche a comprendre le monde."},
  {"question":"qu'est-ce que la science","answer":"La science cherche a expliquer le monde avec des methodes rigoureuses et des preuves."},
  {"question":"qu'est-ce que l'histoire","answer":"L'histoire etudie les evenements passes et leur evolution."},
  {"question":"qui est moliere","answer":"Moliere est un grand auteur de theatre francais du XVIIe siecle."},
  {"question":"qu'est-ce que l'instinct","answer":"L'instinct est une reaction naturelle et rapide, souvent automatique."},
  {"question":"qu'est-ce qu'un chat","answer":"Un chat est un animal domestique agile et independant."},
  {"question":"qu'est-ce qu'un chien","answer":"Un chien est un animal domestique souvent tres fidele et sociable."},
  {"question":"qu'est-ce qu'une fusée","answer":"Une fusee est un vehicule concu pour aller tres vite vers l'espace."},
  {"question":"qu'est-ce que l'espace","answer":"L'espace est tout ce qui se trouve au-dela de l'atmosphere terrestre."},
  {"question":"qu'est-ce qu'une planète","answer":"Une planete est un corps celeste qui tourne autour d'une etoile."},
  {"question":"qu'est-ce qu'une etoile","answer":"Une etoile est une enorme boule de gaz qui emet sa propre lumiere."},
  {"question":"qu'est-ce que la lune","answer":"La lune est le satellite naturel de la Terre."},
  {"question":"qu'est-ce que l'atmosphere","answer":"L'atmosphere est la couche de gaz qui entoure la Terre."},
  {"question":"qu'est-ce que la gravite","answer":"La gravite est la force qui attire les corps les uns vers les autres."},
  {"question":"pourquoi le ciel est bleu","answer":"Le ciel parait bleu parce que l'atmosphere diffuse plus les petites longueurs d'onde de la lumiere solaire."},
  {"question":"qu'est-ce que la lumiere","answer":"La lumiere est un rayonnement visible qui permet de voir les objets."},
  {"question":"qu'est-ce qu'un atome","answer":"Un atome est une tres petite unite de matiere."},
  {"question":"qu'est-ce qu'une molecule","answer":"Une molecule est un assemblage d'atomes lies entre eux."},
  {"question":"qu'est-ce que l'electricite","answer":"L'electricite est un phenomene physique lie au mouvement des charges."},
  {"question":"qu'est-ce qu'une energie","answer":"L'energie permet de produire un travail ou un mouvement."},
  {"question":"qu'est-ce qu'une equation","answer":"Une equation est une relation mathematique avec une inconnue."},
  {"question":"qu'est-ce qu'une proportion","answer":"Une proportion compare deux grandeurs de facon egale."},
  {"question":"qu'est-ce qu'un texte argumentatif","answer":"Un texte argumentatif defend une idee avec des arguments et des exemples."},
  {"question":"qu'est-ce qu'un resume","answer":"Un resume garde l'essentiel d'un texte en version plus courte."},
  {"question":"qu'est-ce qu'une reformulation","answer":"Une reformulation exprime la meme idee avec d'autres mots."},
  {"question":"qu'est-ce qu'une correction","answer":"Une correction rend un texte plus juste en orthographe, grammaire et style."},
  {"question":"comment corriger une phrase","answer":"Il faut verifier l'orthographe, les accords, la ponctuation et la clarté."},
  {"question":"comment faire un plan","answer":"On commence par les grandes idees, puis on detaille chaque partie avec des sous-points."},
  {"question":"comment apprendre un cours","answer":"Lis une premiere fois, prends des notes, fais un resume, puis teste-toi avec des questions."},
  {"question":"comment memoriser une lecon","answer":"Repete-la plusieurs fois, explique-la avec tes mots et fais des fiches."},
  {"question":"qu'est-ce qu'un document","answer":"Un document est un support qui contient des informations, du texte ou des donnees."},
  {"question":"qu'est-ce qu'une mémoire","answer":"La memoire est la capacite a garder et retrouver des informations."},
  {"question":"qu'est-ce qu'une relation","answer":"Une relation relie deux elements et indique un lien entre eux."},
  {"question":"qu'est-ce qu'une entité","answer":"Une entite est un element important repere dans un texte, comme une personne ou un lieu."},
  {"question":"qu'est-ce qu'une personne","answer":"Une personne est un etre humain identifie dans un texte."},
  {"question":"qu'est-ce qu'un lieu","answer":"Un lieu est un endroit, comme une ville, un pays ou un batiment."},
  {"question":"qu'est-ce qu'une date","answer":"Une date indique un moment precis dans le temps."},
  {"question":"qu'est-ce qu'une organisation","answer":"Une organisation est un groupe structure, comme une entreprise ou une association."}
]
